odbms/__init__.py
odbms/cli.py
odbms/connection_pool.py
odbms/database.py
odbms/dbms.py
odbms/fields.py
odbms/migrations.py
odbms/model.py
odbms/mongo_model.py
odbms/new_model.py
odbms/validators.py
odbms/orms/__init__.py
odbms/orms/base.py
odbms/orms/mongodb.py
odbms/orms/mysqldb.py
odbms/orms/postgresqldb.py
odbms/orms/sqlitedb.py
odbms-0.4.5.dist-info/licenses/LICENSE
odbms-0.4.5.dist-info/METADATA
odbms-0.4.5.dist-info/WHEEL
odbms-0.4.5.dist-info/entry_points.txt
odbms-0.4.5.dist-info/top_level.txt
odbms-0.4.5.dist-info/RECORD
