Metadata-Version: 2.4
Name: odbms
Version: 0.4.5
Summary: Database client for Mysql, MongoDB and Sqlite
Author: Amos Amissah
Author-email: theonlyamos@gmail.com
Project-URL: Source, https://github.com/theonlyamos/odbms/
Project-URL: Tracker, https://github.com/theonlyamos/odbms/issues
Keywords: python3 runit developer serverless architecture docker sqlite mysql mongodb
Classifier: Development Status :: 3 - Alpha
Classifier: Intended Audience :: Developers
Classifier: Topic :: Software Development :: Build Tools
Classifier: License :: OSI Approved :: MIT License
Classifier: Programming Language :: Python :: 3
Classifier: Programming Language :: Python :: 3.6
Classifier: Programming Language :: Python :: 3.7
Classifier: Programming Language :: Python :: 3.8
Classifier: Programming Language :: Python :: 3.9
Classifier: Programming Language :: Python :: 3.10
Classifier: Programming Language :: Python :: 3.11
Classifier: Programming Language :: Python :: 3.12
License-File: LICENSE
Requires-Dist: python-dotenv
Requires-Dist: motor
Requires-Dist: aiopg
Requires-Dist: aiomysql
Requires-Dist: inflect
Requires-Dist: pydantic
Requires-Dist: pyreadline3
Dynamic: author
Dynamic: author-email
Dynamic: classifier
Dynamic: description
Dynamic: description-content-type
Dynamic: keywords
Dynamic: license-file
Dynamic: project-url
Dynamic: requires-dist
Dynamic: summary
